ndp_ep/__init__.py
ndp_ep/api_client.py
ndp_ep/client_base.py
ndp_ep/dataset_resource_method.py
ndp_ep/delete_organization_method.py
ndp_ep/delete_resource_method.py
ndp_ep/get_kafka_details_method.py
ndp_ep/get_system_status_method.py
ndp_ep/get_user_info_method.py
ndp_ep/list_organization_method.py
ndp_ep/pelican_method.py
ndp_ep/register_dataset_method.py
ndp_ep/register_kafka_method.py
ndp_ep/register_organization_method.py
ndp_ep/register_s3_method.py
ndp_ep/register_service_method.py
ndp_ep/register_url_method.py
ndp_ep/resource_method.py
ndp_ep/rexec_method.py
ndp_ep/s3_buckets_method.py
ndp_ep/s3_objects_method.py
ndp_ep/search_method.py
ndp_ep/update_dataset_method.py
ndp_ep/update_kafka_method.py
ndp_ep/update_s3_method.py
ndp_ep/update_service_method.py
ndp_ep/update_url_method.py
ndp_ep/version_config.py
ndp_ep-0.6.0.dist-info/licenses/LICENSE
ndp_ep-0.6.0.dist-info/METADATA
ndp_ep-0.6.0.dist-info/WHEEL
ndp_ep-0.6.0.dist-info/top_level.txt
ndp_ep-0.6.0.dist-info/RECORD
