Metadata-Version: 2.4
Name: ndp-ep
Version: 0.6.0
Summary: Python client library for NDP EP API
Author-email: Your Name <your.email@example.com>
License: MIT
Project-URL: Homepage, https://github.com/sci-ndp/ndp-ep-py
Project-URL: Repository, https://github.com/sci-ndp/ndp-ep-py
Project-URL: Documentation, https://github.com/sci-ndp/ndp-ep-py#readme
Project-URL: Bug Tracker, https://github.com/sci-ndp/ndp-ep-py/issues
Keywords: api,client,ndp,ep
Classifier: Development Status :: 4 - Beta
Classifier: Intended Audience :: Developers
Classifier: License :: OSI Approved :: MIT License
Classifier: Operating System :: OS Independent
Classifier: Programming Language :: Python :: 3
Classifier: Programming Language :: Python :: 3.8
Classifier: Programming Language :: Python :: 3.9
Classifier: Programming Language :: Python :: 3.10
Classifier: Programming Language :: Python :: 3.11
Classifier: Programming Language :: Python :: 3.12
Classifier: Topic :: Software Development :: Libraries :: Python Modules
Classifier: Topic :: Internet :: WWW/HTTP :: Dynamic Content
Requires-Python: >=3.8
License-File: LICENSE
Requires-Dist: requests>=2.25.0
Requires-Dist: urllib3>=1.26.0
Requires-Dist: PyJWT>=2.8.0
Provides-Extra: rexec
Requires-Dist: scidx-rexec>=0.0.0; extra == "rexec"
Provides-Extra: dev
Requires-Dist: pytest>=7.0.0; extra == "dev"
Requires-Dist: pytest-cov>=4.0.0; extra == "dev"
Requires-Dist: pytest-mock>=3.10.0; extra == "dev"
Requires-Dist: requests-mock>=1.9.0; extra == "dev"
Requires-Dist: black>=22.0.0; extra == "dev"
Requires-Dist: flake8>=5.0.0; extra == "dev"
Requires-Dist: mypy>=1.0.0; extra == "dev"
Requires-Dist: twine>=4.0.0; extra == "dev"
Requires-Dist: build>=0.10.0; extra == "dev"
Dynamic: license-file
